AUTHORS
ChangeLog
Readme.rst
requirements.txt
setup.cfg
setup.py
tqueues/__init__.py
tqueues.egg-info/PKG-INFO
tqueues.egg-info/SOURCES.txt
tqueues.egg-info/dependency_links.txt
tqueues.egg-info/entry_points.txt
tqueues.egg-info/not-zip-safe
tqueues.egg-info/pbr.json
tqueues.egg-info/requires.txt
tqueues.egg-info/top_level.txt