Metadata-Version: 1.1
Name: tqueues
Version: 0.1.2
Summary: Rethinkdb job queues
Home-page: https://github.com/XayOn/tqueues
Author: David Francos Cuartero
Author-email: opensource@davidfrancos.net
License: Apache-2
Keywords: jobs
Platform: UNKNOWN
Classifier: Development Status :: 4 - Beta
Classifier: Environment :: Console
Classifier: Intended Audience :: Information Technology
Classifier: License :: OSI Approved :: GNU General Public License (GPL)
Classifier: Operating System :: POSIX :: Linux
Classifier: Programming Language :: Python
